st_sigma/__init__.py
st_sigma/example.py
st_sigma/frontend/build/index.html
st_sigma/frontend/build/assets/index-BteNYVWB.css
st_sigma/frontend/build/assets/index-C8evS2KN.js
streamlit_sigmajs-0.1.1.dist-info/licenses/LICENSE
streamlit_sigmajs-0.1.1.dist-info/METADATA
streamlit_sigmajs-0.1.1.dist-info/WHEEL
streamlit_sigmajs-0.1.1.dist-info/top_level.txt
streamlit_sigmajs-0.1.1.dist-info/RECORD
