Metadata-Version: 2.4
Name: streamlit-sigmajs
Version: 0.1.1
Summary: Add your description here
Home-page: 
Author: John Smith
Author-email: john@example.com
Project-URL: Homepage, https://github.com/yourusername/my-package
Project-URL: Repository, https://github.com/yourusername/my-package
Requires-Python: >=3.7
License-File: LICENSE
Requires-Dist: streamlit>=1.50.0
Dynamic: author
Dynamic: author-email
Dynamic: license-file
Dynamic: requires-python
